Metadata-Version: 1.1
Name: pySpam
Version: 0.0.1
Summary: Text spam with PySpam
Home-page: UNKNOWN
Author: Joshua Lowe
Author-email: josh@edublocks.org
License: MIT
Keywords: pySpam
Platform: UNKNOWN
Classifier: Development Status :: 5 - Production/Stable
Classifier: Intended Audience :: Education
Classifier: Operating System :: Microsoft :: Windows :: Windows 10
Classifier: License :: OSI Approved :: MIT License
Classifier: Programming Language :: Python :: 3
